vargur_sdk/__init__.py
vargur_sdk/auth.py
vargur_sdk/cache.py
vargur_sdk/config.py
vargur_sdk/core.py
vargur_sdk/database.py
vargur_sdk/events.py
vargur_sdk/models.py
vargur_sdk-0.1.2.dist-info/LICENSE
vargur_sdk-0.1.2.dist-info/METADATA
vargur_sdk-0.1.2.dist-info/WHEEL
vargur_sdk-0.1.2.dist-info/top_level.txt
vargur_sdk-0.1.2.dist-info/RECORD
