Metadata-Version: 2.1
Name: vargur-sdk
Version: 0.1.2
Summary: A powerful SDK for building extensible applications with plugin support
Home-page: https://github.com/meloncafe/vargur-sdk
Author: MelonCafe
Author-email: contact@siege-green.com
Classifier: Development Status :: 3 - Alpha
Classifier: Intended Audience :: Developers
Classifier: License :: OSI Approved :: MIT License
Classifier: Operating System :: OS Independent
Classifier: Programming Language :: Python :: 3
Classifier: Programming Language :: Python :: 3.11
Requires-Python: >=3.11
License-File: LICENSE
Requires-Dist: fastapi
Provides-Extra: dev
Requires-Dist: pytest ; extra == 'dev'
Requires-Dist: pytest-asyncio ; extra == 'dev'
